<?xml version="1.0" encoding="utf-8"?><DEFECTS><DEFECT>
    <SFA>
      <FILEPATH>C:\Users\Felix\Documents\git\captain_comic\</FILEPATH>
      <FILENAME>comic.c</FILENAME>
      <LINE>77</LINE>
      <COLUMN>19</COLUMN>
    </SFA>
    <DEFECTCODE>26451</DEFECTCODE>
    <DESCRIPTION>Arithmetischer Überlauf: Wenn Sie den Operator "*" für einen 4-Bytewert verwenden und das Ergebnis in einen 8-Bytewert umwandeln, wandeln Sie den Wert in den breiteren Typ um, bevor Sie den Operator "*" verwenden, um einen Überlauf zu vermeiden (io.2).</DESCRIPTION>
    <FUNCTION>wait_n_ticks</FUNCTION>
    <DECORATED>wait_n_ticks</DECORATED>
    <FUNCLINE>75</FUNCLINE>
    <PATH></PATH>
  </DEFECT><DEFECT>
    <SFA>
      <FILEPATH>C:\Users\Felix\Documents\git\captain_comic\</FILEPATH>
      <FILENAME>comic.c</FILENAME>
      <LINE>458</LINE>
      <COLUMN>5</COLUMN>
    </SFA>
    <DEFECTCODE>6262</DEFECTCODE>
    <DESCRIPTION>Die Funktion verwendet "16400" Bytes vom Stapel und überschreitet /analyze:stacksize "16384". Verschieben Sie einige Daten auf den Heap.</DESCRIPTION>
    <FUNCTION>blank_door_offscreen</FUNCTION>
    <DECORATED>blank_door_offscreen</DECORATED>
    <FUNCLINE>458</FUNCLINE>
    <PATH></PATH>
  </DEFECT><DEFECT>
    <SFA>
      <FILEPATH>C:\Users\Felix\Documents\git\captain_comic\</FILEPATH>
      <FILENAME>comic.c</FILENAME>
      <LINE>908</LINE>
      <COLUMN>22</COLUMN>
    </SFA>
    <DEFECTCODE>26451</DEFECTCODE>
    <DESCRIPTION>Arithmetischer Überlauf: Wenn Sie den Operator "*" für einen 4-Bytewert verwenden und das Ergebnis in einen 8-Bytewert umwandeln, wandeln Sie den Wert in den breiteren Typ um, bevor Sie den Operator "*" verwenden, um einen Überlauf zu vermeiden (io.2).</DESCRIPTION>
    <FUNCTION>render_map</FUNCTION>
    <DECORATED>render_map</DECORATED>
    <FUNCLINE>883</FUNCLINE>
    <PATH></PATH>
  </DEFECT></DEFECTS>